problog/__init__.py
problog/__main__.py
problog/bdd_formula.py
problog/bdd_formula_alt.py
problog/clausedb.py
problog/cnf_formula.py
problog/constraint.py
problog/core.py
problog/cycles.py
problog/dd_formula.py
problog/ddnnf_formula.py
problog/debug.py
problog/engine.py
problog/engine_builtin.py
problog/engine_stack.py
problog/engine_unify.py
problog/errors.py
problog/eval_nodes.py
problog/evaluator.py
problog/extern.py
problog/formula.py
problog/forward.py
problog/ground_yap.py
problog/kbest.py
problog/logic.py
problog/magic.py
problog/maxsat.py
problog/nnf_formula.py
problog/parser.py
problog/program.py
problog/pypl.py
problog/sdd_formula.py
problog/sdd_formula_explicit.py
problog/setup.py
problog/util.py
problog/version.py
problog/__pycache__/__init__.cpython-313.pyc
problog/__pycache__/bdd_formula.cpython-313.pyc
problog/__pycache__/clausedb.cpython-313.pyc
problog/__pycache__/cnf_formula.cpython-313.pyc
problog/__pycache__/constraint.cpython-313.pyc
problog/__pycache__/core.cpython-313.pyc
problog/__pycache__/cycles.cpython-313.pyc
problog/__pycache__/dd_formula.cpython-313.pyc
problog/__pycache__/ddnnf_formula.cpython-313.pyc
problog/__pycache__/debug.cpython-313.pyc
problog/__pycache__/engine.cpython-313.pyc
problog/__pycache__/engine_builtin.cpython-313.pyc
problog/__pycache__/engine_stack.cpython-313.pyc
problog/__pycache__/engine_unify.cpython-313.pyc
problog/__pycache__/errors.cpython-313.pyc
problog/__pycache__/eval_nodes.cpython-313.pyc
problog/__pycache__/evaluator.cpython-313.pyc
problog/__pycache__/formula.cpython-313.pyc
problog/__pycache__/forward.cpython-313.pyc
problog/__pycache__/kbest.cpython-313.pyc
problog/__pycache__/logic.cpython-313.pyc
problog/__pycache__/maxsat.cpython-313.pyc
problog/__pycache__/parser.cpython-313.pyc
problog/__pycache__/program.cpython-313.pyc
problog/__pycache__/sdd_formula.cpython-313.pyc
problog/__pycache__/sdd_formula_explicit.cpython-313.pyc
problog/__pycache__/setup.cpython-313.pyc
problog-2.2.9.dist-info/METADATA
problog-2.2.9.dist-info/WHEEL
problog-2.2.9.dist-info/entry_points.txt
problog-2.2.9.dist-info/top_level.txt
problog-2.2.9.dist-info/RECORD
