Metadata-Version: 2.4
Name: problog
Version: 2.2.9
Summary: ProbLog2: Probabilistic Logic Programming toolbox
Home-page: https://dtai.cs.kuleuven.be/problog
Author: ProbLog team
Author-email: anton.dries@cs.kuleuven.be
License: Apache Software License
Keywords: prolog probabilistic logic
Classifier: Development Status :: 4 - Beta
Classifier: License :: OSI Approved :: Apache Software License
Classifier: Intended Audience :: Science/Research
Classifier: Programming Language :: Python :: 3
Classifier: Programming Language :: Python :: 3.8
Classifier: Programming Language :: Python :: 3.9
Classifier: Programming Language :: Python :: 3.10
Classifier: Programming Language :: Python :: 3.11
Classifier: Programming Language :: Python :: 3.12
Classifier: Programming Language :: Prolog
Classifier: Topic :: Scientific/Engineering :: Artificial Intelligence
Requires-Dist: setuptools
Provides-Extra: sdd
Requires-Dist: pysdd>=0.2.6; extra == "sdd"
Dynamic: author
Dynamic: author-email
Dynamic: classifier
Dynamic: description
Dynamic: description-content-type
Dynamic: home-page
Dynamic: keywords
Dynamic: license
Dynamic: provides-extra
Dynamic: requires-dist
Dynamic: summary
